one_team_one_dream/__init__.py
one_team_one_dream/gcp_module.py
one_team_one_dream-0.0.2.dist-info/LICENSE
one_team_one_dream-0.0.2.dist-info/METADATA
one_team_one_dream-0.0.2.dist-info/WHEEL
one_team_one_dream-0.0.2.dist-info/top_level.txt
one_team_one_dream-0.0.2.dist-info/RECORD
